{"ISBN:0061122734": {"info_url": "http://openlibrary.org/books/OL9951895M/Football_Genius", "bib_key": "ISBN:0061122734", "preview_url": "http://openlibrary.org/books/OL9951895M/Football_Genius", "thumbnail_url": "http://covers.openlibrary.org/b/id/6338677-S.jpg", "details": {"publishers": ["HarperTrophy"], "identifiers": {"goodreads": ["2353681"], "librarything": ["3157422"]}, "key": "/books/OL9951895M", "source_records": ["amazon:0061122734"], "created": {"type": "/type/datetime", "value": "2008-04-30T09:38:13.731961"}, "type": {"key": "/type/edition"}, "number_of_pages": 272, "isbn_13": ["9780061122736"], "covers": [6338677], "languages": [{"key": "/languages/eng"}], "isbn_10": ["0061122734"], "latest_revision": 7, "last_modified": {"type": "/type/datetime", "value": "2013-08-31T17:59:32.565754"}, "authors": [{"name": "Green, Tim", "key": "/authors/OL20050A"}], "publish_date": "April 22, 2008", "title": "Football Genius", "works": [{"key": "/works/OL277531W"}], "physical_format": "Paperback", "subjects": ["Action & Adventure - General", "Social Issues - General", "Sports & Recreation - Football", "Juvenile Fiction / Action & Adventure", "Juvenile Fiction", "Children's Books - Young Adult Fiction", "Children: Grades 4-6"], "revision": 7}, "preview": "noview"}}
