{"ISBN:0064402010": {"info_url": "http://openlibrary.org/books/OL9246374M/The_Great_Gilly_Hopkins", "bib_key": "ISBN:0064402010", "preview_url": "http://openlibrary.org/books/OL9246374M/The_Great_Gilly_Hopkins", "thumbnail_url": "http://covers.openlibrary.org/b/id/50015-S.jpg", "details": {"identifiers": {"librarything": ["6314"], "goodreads": ["242858"]}, "weight": "5.6 ounces", "covers": [50015], "latest_revision": 6, "first_sentence": {"type": "/type/text", "value": "\"ILLY\" said Miss Ellis with a shake of her long blonde hair toward the passenger in the back seat."}, "source_records": ["amazon:0064402010:o-4:657710930:268464", "amazon:0064402010:5:173603294:268723"], "title": "The Great Gilly Hopkins", "languages": [{"key": "/languages/eng"}], "subjects": ["Emotions & feelings", "Fiction", "Fiction dealing with family issues", "Fiction dealing with social issues", "Fostering & adoption", "Juvenile Fiction", "Children's Books/Ages 9-12 Fiction", "Children: Grades 4-6", "Social Issues - Adolescence", "Girls & Women", "Juvenile Fiction / Family / Orphans & Foster Homes", "Family - Orphans & Foster Homes", "Social Issues - Emotions & Feelings", "Foster home care"], "type": {"key": "/type/edition"}, "physical_dimensions": "7.5 x 5.1 x 0.6 inches", "revision": 6, "publishers": ["HarperTrophy"], "physical_format": "Paperback", "last_modified": {"type": "/type/datetime", "value": "2010-08-12T02:45:24.431560"}, "key": "/books/OL9246374M", "authors": [{"name": "Katherine Paterson", "key": "/authors/OL26242A"}], "created": {"type": "/type/datetime", "value": "2008-04-30T09:38:13.731961"}, "number_of_pages": 148, "isbn_13": ["9780064402019"], "isbn_10": ["0064402010"], "publish_date": "April 13, 2004", "works": [{"key": "/works/OL27124W"}]}, "preview": "noview"}}
