{"ISBN:0142410381": {"info_url": "http://openlibrary.org/books/OL9315797M/The_BFG", "bib_key": "ISBN:0142410381", "preview_url": "http://openlibrary.org/books/OL9315797M/The_BFG", "thumbnail_url": "http://covers.openlibrary.org/b/id/1119240-S.jpg", "details": {"number_of_pages": 208, "weight": "4 ounces", "covers": [1119240], "latest_revision": 6, "contributions": ["Quentin Blake (Illustrator)"], "edition_name": "Reprint edition", "source_records": ["amazon:0142410381:2-aa:2598487567:308220"], "title": "The BFG", "languages": [{"key": "/languages/eng"}], "subjects": ["Juvenile Fiction", "Children's Books/Ages 9-12 Fiction", "Children's Books/All Ages", "Children: Grades 4-6", "Action & Adventure - General", "Classics", "Humorous Stories", "Juvenile Fiction / Action & Adventure", "Family - Orphans & Foster Homes", "Science Fiction, Fantasy, & Magic", "Fantastic fiction", "Fiction", "Giants", "Orphans"], "type": {"key": "/type/edition"}, "physical_dimensions": "7.6 x 4.9 x 0.8 inches", "revision": 6, "publishers": ["Puffin"], "physical_format": "Paperback", "last_modified": {"type": "/type/datetime", "value": "2010-08-12T04:19:24.528948"}, "key": "/books/OL9315797M", "authors": [{"name": "Roald Dahl", "key": "/authors/OL34184A"}], "created": {"type": "/type/datetime", "value": "2008-04-30T09:38:13.731961"}, "identifiers": {"librarything": ["1513"], "goodreads": ["99474"]}, "isbn_13": ["9780142410387"], "isbn_10": ["0142410381"], "publish_date": "August 16, 2007", "works": [{"key": "/works/OL45885W"}]}, "preview": "noview"}}
