{"ISBN:0399236260": {"info_url": "http://openlibrary.org/books/OL23246569M/Things_not_seen", "bib_key": "ISBN:0399236260", "preview_url": "http://www.archive.org/details/thingsnotseen00clem", "thumbnail_url": "http://covers.openlibrary.org/b/id/6569330-S.jpg", "details": {"number_of_pages": 251, "covers": [6569330], "ia_loaded_id": ["thingsnotseen00clem_0"], "latest_revision": 9, "ocaid": "thingsnotseen00clem", "description": {"type": "/type/text", "value": "When fifteen-year-old Bobby wakes up and finds himself invisible, he and his parents and his new blind friend Alicia try to find out what caused his condition and how to reverse it."}, "genres": ["Juvenile fiction"], "source_records": ["marc:CollingswoodLibraryMarcDump10-27-2008/Collingswood.out:29456280:2029", "ia:thingsnotseen00clem", "ia:thingsnotseen00clem_0", "marc:marc_loc_updates/v40.i08.records.utf8:196332:1002"], "title": "Things not seen", "languages": [{"key": "/languages/eng"}], "subjects": ["Blind -- Juvenile fiction", "People with disabilities -- Juvenile fiction", "Science fiction -- Juvenile fiction"], "publish_country": "nyu", "by_statement": "Andrew Clements.", "type": {"key": "/type/edition"}, "revision": 9, "publishers": ["Philomel Books"], "ia_box_id": ["IA176801"], "last_modified": {"type": "/type/datetime", "value": "2012-02-22T05:55:40.143165"}, "key": "/books/OL23246569M", "authors": [{"name": "Clements, Andrew", "key": "/authors/OL29483A"}], "publish_places": ["New York"], "pagination": "251 p. ;", "created": {"type": "/type/datetime", "value": "2009-05-29T11:36:30.825643"}, "lccn": ["00069900"], "identifiers": {"goodreads": ["542752", "331954"], "librarything": ["35375"]}, "isbn_10": ["0142400769", "0399236260"], "publish_date": "2002", "works": [{"key": "/works/OL102514W"}]}, "preview": "restricted"}}
