{"ISBN:0439319420": {"bib_key": "ISBN:0439319420", "preview": "noview", "preview_url": "http://openlibrary.org/books/OL7511882M/Fluffy_the_Secret_Santa_(Hello_Reader!_Level_3_(Book_Club_Only))", "info_url": "http://openlibrary.org/books/OL7511882M/Fluffy_the_Secret_Santa_(Hello_Reader!_Level_3_(Book_Club_Only))", "details": {"publishers": ["Scholastic"], "languages": [{"key": "/languages/eng"}], "number_of_pages": 1, "key": "/books/OL7511882M", "title": "Fluffy, the Secret Santa (Hello Reader!, Level 3 (Book Club Only))", "contributions": ["Mavis Smith (Illustrator)"], "identifiers": {"goodreads": ["1564950"], "librarything": ["1208770"]}, "created": {"type": "/type/datetime", "value": "2008-04-29T13:35:46.876380"}, "isbn_13": ["9780439319423"], "isbn_10": ["0439319420"], "latest_revision": 6, "last_modified": {"type": "/type/datetime", "value": "2011-04-28T17:31:25.110170"}, "authors": [{"name": "Kate McMullan", "key": "/authors/OL21413A"}], "publish_date": "May 2002", "oclc_numbers": ["46858439"], "works": [{"key": "/works/OL15042942W"}], "type": {"key": "/type/edition"}, "revision": 6}}}
