{"ISBN:0006921566": {"bib_key": "ISBN:0006921566", "preview": "noview", "preview_url": "http://openlibrary.org/books/OL9921465M/The_Hidden_Staircase_(Nancy_Drew_Mysteries)", "info_url": "http://openlibrary.org/books/OL9921465M/The_Hidden_Staircase_(Nancy_Drew_Mysteries)", "details": {"publishers": ["HarperCollins Publishers"], "number_of_pages": 160, "type": {"key": "/type/edition"}, "key": "/books/OL9921465M", "title": "The Hidden Staircase (Nancy Drew Mysteries)", "series": ["Nancy Drew (2)"], "identifiers": {"goodreads": ["914261"], "librarything": ["38494"]}, "created": {"type": "/type/datetime", "value": "2008-04-30T09:38:13.731961"}, "isbn_13": ["9780006921561"], "isbn_10": ["0006921566"], "latest_revision": 6, "last_modified": {"type": "/type/datetime", "value": "2011-04-26T23:17:25.053706"}, "authors": [{"name": "Carolyn Keene", "key": "/authors/OL29614A"}], "publish_date": "May 12, 1983", "oclc_numbers": ["59803421"], "works": [{"key": "/works/OL39827W"}], "physical_format": "Paperback", "subjects": ["Crime & mystery"], "revision": 6}}}
