{"ISBN:0756625394": {"info_url": "http://openlibrary.org/books/OL7995509M/First_Dinosaur_Encyclopedia", "bib_key": "ISBN:0756625394", "preview_url": "http://openlibrary.org/books/OL7995509M/First_Dinosaur_Encyclopedia", "thumbnail_url": "http://covers.openlibrary.org/b/id/1414785-S.jpg", "details": {"publishers": ["DK CHILDREN"], "number_of_pages": 128, "key": "/books/OL7995509M", "weight": "1.2 pounds", "title": "First Dinosaur Encyclopedia", "type": {"key": "/type/edition"}, "identifiers": {"librarything": ["4824100"], "goodreads": ["555198"]}, "isbn_13": ["9780756625399"], "covers": [1414785], "created": {"type": "/type/datetime", "value": "2008-04-29T15:03:11.581851"}, "languages": [{"key": "/languages/eng"}], "isbn_10": ["0756625394"], "latest_revision": 6, "last_modified": {"type": "/type/datetime", "value": "2010-08-06T21:03:10.301865"}, "authors": [{"name": "DK Publishing", "key": "/authors/OL2655350A"}], "publish_date": "December 18, 2006", "works": [{"key": "/works/OL7958612W"}], "physical_format": "Hardcover", "subjects": ["Juvenile Paleontology", "Juvenile Nonfiction", "Children's Books/Ages 4-8 Nonfiction", "Children: Grades 1-2", "Animals - Dinosaurs & Prehistoric Creatures", "Reference - Encyclopedias", "Juvenile Nonfiction / Animals / Dinosaurs", "Dinosaurs", "Encyclopedias, Juvenile"], "physical_dimensions": "10.8 x 8.5 x 0.5 inches", "revision": 6}, "preview": "noview"}}
